[1,["85W4JbNPFJNYVqZ4yXHeF9@f9941","bfdHtVdpJDd6siog0RWiOe@f9941","d0/ZWiCY5Jfp/3G6pzH3IJ@f9941","85W4JbNPFJNYVqZ4yXHeF9@6c48a","bfdHtVdpJDd6siog0RWiOe@6c48a"],["node","_spriteFrame","_textureSource","root","data"],[["cc.Node",["_name","_layer","_components","_prefab","_parent","_children","_lpos"],1,9,4,1,2,5],"cc.SpriteFrame",["cc.Sprite",["_sizeMode","_type","node","__prefab","_spriteFrame"],1,1,4,6],["cc.Prefab",["_name"],2],["cc.UITransform",["node","__prefab","_contentSize"],3,1,4,5],["cc.CompPrefabInfo",["fileId"],2],["cc.PrefabInfo",["fileId","instance","targetOverrides","nestedPrefabInstanceRoots","root","asset"],-1,1,1],["cc.Mask",["_type","node","__prefab"],2,1,4],["cc.Label",["_string","_actualFontSize","_fontSize","node","__prefab"],0,1,4]],[[5,0,2],[4,0,1,2,1],[6,0,1,2,3,4,5,5],[0,0,1,4,2,3,6,3],[2,0,2,3,4,2],[8,0,1,2,3,4,4],[3,0,2],[0,0,1,5,2,3,3],[0,0,1,4,5,2,3,3],[0,0,1,4,2,3,3],[7,0,1,2,2],[2,1,0,2,3,4,3]],[[[[6,"CommsPlayer1"],[7,"CommsPlayer1",33554432,[-3,-4,-5,-6],[[1,-2,[0,"ebXFuzmmtBlY4CswDFGaQM"],[5,140,140]]],[2,"c46/YsCPVOJYA4mWEpNYRx",null,null,null,-1,0]],[8,"head_mask",33554432,1,[-10],[[1,-7,[0,"b5WnLuFZtJppJP7tKMX5dz"],[5,130,130]],[10,3,-8,[0,"5b+Et7W2lOUqKK+83mEZc2"]],[4,0,-9,[0,"a6JYRVw9RA2r6uoHbLpfFu"],1]],[2,"97pb5DIclCqK8tdqlwmvwU",null,null,null,1,0]],[9,"head_icon",33554432,2,[[1,-11,[0,"f6X5vqaEZAl5fdVThTTjeR"],[5,130,130]],[4,0,-12,[0,"62MTp0rtZFopsUK0d9PW0E"],0]],[2,"4aZKU3PdlCt6JnrTAOqKYW",null,null,null,1,0]],[3,"bg_gold",33554432,1,[[1,-13,[0,"9c4KESELFFoZK3KQP6arX8"],[5,140,42]],[11,1,0,-14,[0,"6bqBhKpYNDMoMXWGUZpiN5"],2]],[2,"19JQ3iWnFMhboFcigF7dbt",null,null,null,1,0],[1,0,-86,0]],[3,"lb_gold",33554432,1,[[1,-15,[0,"0f+2P7eQFOaaufVC7F7VUE"],[5,20.021484375,50.4]],[5,"0",36,36,-16,[0,"17ll5WcMlOqK9vvf9Z2ZzQ"]]],[2,"afYSqeW89MVJ2OSINYrtU3",null,null,null,1,0],[1,0,-86,0]],[3,"lb_name",33554432,1,[[1,-17,[0,"57ULcxa7NCuqIDNaCbeccF"],[5,68,50.4]],[5,"名字",34,34,-18,[0,"cb1PvS3uRIzak/tKyG7L1P"]]],[2,"a2S2mUCDFF5raZkdNYANWf",null,null,null,1,0],[1,0,87,0]]],0,[0,3,1,0,0,1,0,-1,2,0,-2,4,0,-3,5,0,-4,6,0,0,2,0,0,2,0,0,2,0,-1,3,0,0,3,0,0,3,0,0,4,0,0,4,0,0,5,0,0,5,0,0,6,0,0,6,0,4,1,18],[0,0,0],[1,1,1],[0,1,2]],[[{"name":"head_dark","rect":{"x":0,"y":0,"width":96,"height":96},"offset":{"x":0,"y":0},"originalSize":{"width":96,"height":96},"rotated":false,"capInsets":[0,0,0,0],"vertices":{"rawPosition":[-48,-48,0,48,-48,0,-48,48,0,48,48,0],"indexes":[0,1,2,2,1,3],"uv":[0,96,96,96,0,0,96,0],"nuv":[0,0,1,0,0,1,1,1],"minPos":{"x":-48,"y":-48,"z":0},"maxPos":{"x":48,"y":48,"z":0}},"packable":true,"pixelsToUnit":100,"pivot":{"x":0.5,"y":0.5},"meshType":0}],[1],0,[0],[2],[3]],[[{"name":"head_mask","rect":{"x":0,"y":0,"width":100,"height":100},"offset":{"x":0,"y":0},"originalSize":{"width":100,"height":100},"rotated":false,"capInsets":[0,0,0,0],"vertices":{"rawPosition":[-50,-50,0,50,-50,0,-50,50,0,50,50,0],"indexes":[0,1,2,2,1,3],"uv":[0,100,100,100,0,0,100,0],"nuv":[0,0,1,0,0,1,1,1],"minPos":{"x":-50,"y":-50,"z":0},"maxPos":{"x":50,"y":50,"z":0}},"packable":true,"pixelsToUnit":100,"pivot":{"x":0.5,"y":0.5},"meshType":0}],[1],0,[0],[2],[4]]]]
